eventzAPI.py
eventzAPI-2.2.6.dist-info/LICENSE
eventzAPI-2.2.6.dist-info/METADATA
eventzAPI-2.2.6.dist-info/WHEEL
eventzAPI-2.2.6.dist-info/entry_points.txt
eventzAPI-2.2.6.dist-info/top_level.txt
eventzAPI-2.2.6.dist-info/RECORD
