Metadata-Version: 2.1
Name: eventzAPI
Version: 2.2.6
Summary: The Events API supports a Python micro-services infrastructure using RabbitMQ, Event Sourcing & Tuple Space
Author-email: "I-Technology Inc." <bobj@i-technologyinc.com>
License: GNU GENERAL PUBLIC LICENSE
Project-URL: Homepage, https://www.eventzapi.com/
Project-URL: Repository, https://github.com/i-Technology/eventzAPI.git
Keywords: microservice,API,events
Classifier: Programming Language :: Python :: 3.12
Classifier: Natural Language :: English
Classifier: Topic :: System :: Distributed Computing
Classifier: Intended Audience :: Developers
Classifier: License :: OSI Approved :: GNU Lesser General Public License v3 or later (LGPLv3+)
Classifier: Operating System :: OS Independent
Requires-Python: >=3.12
License-File: LICENSE
Requires-Dist: PyQt6
Requires-Dist: tomli ; python_version < "3.11"
Provides-Extra: dev
